cryro/__init__.py
cryro/getdata.py
cryro-1.0.0.dist-info/LICENSE
cryro-1.0.0.dist-info/METADATA
cryro-1.0.0.dist-info/WHEEL
cryro-1.0.0.dist-info/top_level.txt
cryro-1.0.0.dist-info/RECORD
