Metadata-Version: 2.1
Name: cryro
Version: 1.0.0
Summary: A simple Python package
Home-page: https://github.com/BRAINIFII/cryro
Author: your name
Author-email: bangerakritik.alt@gmail.com
Classifier: Programming Language :: Python :: 3
Classifier: License :: OSI Approved :: MIT License
Classifier: Operating System :: OS Independent
Requires-Python: >=3.6
License-File: LICENSE
Requires-Dist: tinyec
Requires-Dist: bs4
Requires-Dist: requests
